Metadata-Version: 2.1
Name: odoo12-addon-l10n-it-invoices-data-communication-fatturapa
Version: 12.0.1.0.2
Summary: Integrazione fatturazione elettronica e comunicazione dati fatture (c.d. "nuovo spesometro")
Home-page: https://github.com/OCA/l10n-italy/
Author: Agile Business Group, Odoo Community Association (OCA)
Author-email: support@odoo-community.org
License: AGPL-3
Platform: UNKNOWN
Classifier: Programming Language :: Python
Classifier: Framework :: Odoo
Classifier: License :: OSI Approved :: GNU Affero General Public License v3
Requires-Python: >=3.5
Requires-Dist: odoo12-addon-l10n-it-fatturapa-in
Requires-Dist: odoo12-addon-l10n-it-fatturapa-out
Requires-Dist: odoo12-addon-l10n-it-invoices-data-communication
Requires-Dist: odoo (<12.1dev,>=12.0a)
